LICENSE
README.md
pyproject.toml
setup.py
sbioapputils/__init__.py
sbioapputils.egg-info/PKG-INFO
sbioapputils.egg-info/SOURCES.txt
sbioapputils.egg-info/dependency_links.txt
sbioapputils.egg-info/requires.txt
sbioapputils.egg-info/top_level.txt
sbioapputils/app_runner/__init__.py
sbioapputils/app_runner/app_runner_utils.py
sbioapputils/app_runner/dev_utils.py
sbioapputils/app_runner/templates.py
sbioapputils/app_runner/workflow_utils.py
sbioapputils/app_runner/yaml_automation.py
sbioapputils/app_runner/yaml_utils.py
sbioapputils/load/constants.py
sbioapputils/load/decompress.py
sbioapputils/load/load_data.py