Metadata-Version: 1.0
Name: sbioapputils
Version: 1.0.26
Summary: Superbio app runner utils
Home-page: https://github.com/Superbio-ai/app-sbioutils
Author: Superbio AI
Author-email: smorgan@superbio.ai
License: UNKNOWN
Platform: UNKNOWN
